dependency_resolver/__init__.py
dependency_resolver/constants.py
dependency_resolver/resolve.py
dependency_resolver/setup.py
dependency_resolver/resolver/__init__.py
dependency_resolver/resolver/cache/__init__.py
dependency_resolver/resolver/cache/cache.py
dependency_resolver/resolver/configuration/__init__.py
dependency_resolver/resolver/configuration/attributes.py
dependency_resolver/resolver/configuration/configuration.py
dependency_resolver/resolver/dependencies/__init__.py
dependency_resolver/resolver/dependencies/dependencies.py
dependency_resolver/resolver/dependencies/dependency.py
dependency_resolver/resolver/dependencies/resolveAction.py
dependency_resolver/resolver/errors/__init__.py
dependency_resolver/resolver/errors/errors.py
dependency_resolver/resolver/project/__init__.py
dependency_resolver/resolver/project/creator.py
dependency_resolver/resolver/project/project.py
dependency_resolver/resolver/sources/__init__.py
dependency_resolver/resolver/sources/protocol.py
dependency_resolver/resolver/sources/source.py
dependency_resolver/resolver/sources/sources.py
dependency_resolver/resolver/sources/type.py
dependency_resolver/resolver/utilities/__init__.py
dependency_resolver/resolver/utilities/alive_util.py
dependency_resolver/resolver/utilities/dependencies_util.py
dependency_resolver/resolver/utilities/errors_util.py
dependency_resolver/resolver/utilities/file_util.py
dependency_resolver/resolver/utilities/helpers.py
dependency_resolver/resolver/utilities/https_util.py
dependency_resolver/resolver/utilities/json_util.py
dependency_resolver/resolver/utilities/log_util.py
dependency_resolver/resolver/utilities/run_util.py
dependency_resolver/resolver/utilities/tar_util.py
dependency_resolver/resolver/utilities/time_util.py
dependency_resolver/resolver/utilities/zip_util.py
dependency_resolver-1.0.2.dist-info/licenses/LICENSE
dependency_resolver-1.0.2.dist-info/METADATA
dependency_resolver-1.0.2.dist-info/WHEEL
dependency_resolver-1.0.2.dist-info/entry_points.txt
dependency_resolver-1.0.2.dist-info/top_level.txt
dependency_resolver-1.0.2.dist-info/RECORD
