Metadata-Version: 2.4
Name: dependency-resolver
Version: 1.0.2
Summary: "A way to specify publicly available sources (e.g. files/zips) to cache locally and then resolve these sources (e.g. copy/unzip) to a local directories for use."
Home-page: https://github.com/dan-east/dependency-resolver
Author: Dan East
Requires-Python: >=3.10
License-File: LICENSE
Requires-Dist: requests
Requires-Dist: python-dotenv
Requires-Dist: StrEnum; python_version < "3.11"
Provides-Extra: test
Requires-Dist: pytest; extra == "test"
Dynamic: license-file
